{
	"id": "tooth-tycoon-prod-env",
	"name": "Tooth Tycoon - Production",
	"values": [
		{
			"key": "base_url",
			"value": "https://api.toothtycoon.com",
			"type": "default",
			"enabled": true
		},
		{
			"key": "access_token",
			"value": "",
			"type": "secret",
			"enabled": true
		},
		{
			"key": "user_id",
			"value": "",
			"type": "default",
			"enabled": true
		},
		{
			"key": "user_email",
			"value": "",
			"type": "default",
			"enabled": true
		},
		{
			"key": "user_password",
			"value": "",
			"type": "secret",
			"enabled": true
		}
	],
	"_postman_variable_scope": "environment"
}
